k_selenium_cookies/__init__.py
k_selenium_cookies/cookies.py
k_selenium_cookies/models/__init__.py
k_selenium_cookies/models/cookie.py
k_selenium_cookies-0.0.4.dist-info/LICENSE
k_selenium_cookies-0.0.4.dist-info/METADATA
k_selenium_cookies-0.0.4.dist-info/WHEEL
k_selenium_cookies-0.0.4.dist-info/top_level.txt
k_selenium_cookies-0.0.4.dist-info/RECORD
